LICENSE
MANIFEST.in
README.rst
setup.cfg
setup.py
craigslist_meta/__init__.py
craigslist_meta/api.py
craigslist_meta/base.py
craigslist_meta/metadata.py
python_craigslist_meta.egg-info/PKG-INFO
python_craigslist_meta.egg-info/SOURCES.txt
python_craigslist_meta.egg-info/dependency_links.txt
python_craigslist_meta.egg-info/top_level.txt