Metadata-Version: 1.1
Name: python-craigslist-meta
Version: 0.3.1
Summary: A simple API to traverse Craigslist endpoints
Home-page: https://github.com/irahorecka/python-craigslist-meta
Author: Ira Horecka
Author-email: ira89@icloud.com
License: MIT
Platform: UNKNOWN
Classifier: Programming Language :: Python :: 3.5
Classifier: Programming Language :: Python :: 3.6
Classifier: Programming Language :: Python :: 3.7
Classifier: Programming Language :: Python :: 3.8
Classifier: Programming Language :: Python :: 3.9
Classifier: Intended Audience :: Developers
Classifier: License :: OSI Approved :: MIT License
Classifier: Topic :: Software Development :: Libraries
Classifier: Topic :: Utilities
